vara_pygelf/__init__.py
vara_pygelf/logger.py
vara_pygelf-0.0.3.dist-info/LICENSE
vara_pygelf-0.0.3.dist-info/METADATA
vara_pygelf-0.0.3.dist-info/WHEEL
vara_pygelf-0.0.3.dist-info/top_level.txt
vara_pygelf-0.0.3.dist-info/RECORD
