Metadata-Version: 2.1
Name: vara-pygelf
Version: 0.0.3
Summary: gelf formatted logger
Author-email: Varadise <author@example.com>
License: MIT License        
Classifier: Programming Language :: Python :: 3
Classifier: License :: OSI Approved :: MIT License
Requires-Python: >=3.4
License-File: LICENSE
